med_diagnostics/__init__.py
med_diagnostics/_version.py
med_diagnostics/data.py
med_diagnostics/diagnostics.py
med_diagnostics/session.py
med_diagnostics/ui.py
med_diagnostics-1.0.dist-info/LICENSE
med_diagnostics-1.0.dist-info/METADATA
med_diagnostics-1.0.dist-info/WHEEL
med_diagnostics-1.0.dist-info/top_level.txt
med_diagnostics-1.0.dist-info/RECORD
