Metadata-Version: 2.1
Name: med-diagnostics
Version: 1.0
Summary: ACCESS MED-Diagnostics
Author: ACCESS-NRI
License: APACHE-2.0
Classifier: Development Status :: 4 - Beta
Classifier: Programming Language :: Python :: 3
Classifier: License :: OSI Approved :: Apache Software License
Classifier: Operating System :: OS Independent
Requires-Python: >=3.10
License-File: LICENSE
Requires-Dist: apscheduler
Requires-Dist: access-nri-intake
Requires-Dist: panel
Requires-Dist: matplotlib
